.travis.yml
CHANGES.txt
COPYRIGHT.txt
LICENSE.txt
MANIFEST.in
README.txt
bootstrap.py
buildout.cfg
setup.py
src/z3c/__init__.py
src/z3c.jsonrpc.egg-info/PKG-INFO
src/z3c.jsonrpc.egg-info/SOURCES.txt
src/z3c.jsonrpc.egg-info/dependency_links.txt
src/z3c.jsonrpc.egg-info/namespace_packages.txt
src/z3c.jsonrpc.egg-info/not-zip-safe
src/z3c.jsonrpc.egg-info/requires.txt
src/z3c.jsonrpc.egg-info/top_level.txt
src/z3c/jsonrpc/README.txt
src/z3c/jsonrpc/__init__.py
src/z3c/jsonrpc/browser.py
src/z3c/jsonrpc/configure.zcml
src/z3c/jsonrpc/error.py
src/z3c/jsonrpc/error.zcml
src/z3c/jsonrpc/exception.py
src/z3c/jsonrpc/ftesting.zcml
src/z3c/jsonrpc/interfaces.py
src/z3c/jsonrpc/layer.py
src/z3c/jsonrpc/meta.zcml
src/z3c/jsonrpc/namespace.py
src/z3c/jsonrpc/publication.py
src/z3c/jsonrpc/publisher.py
src/z3c/jsonrpc/testing.py
src/z3c/jsonrpc/zcml.py
src/z3c/jsonrpc/zcml.txt
src/z3c/jsonrpc/tests/__init__.py
src/z3c/jsonrpc/tests/page.pt
src/z3c/jsonrpc/tests/test_doc.py
src/z3c/jsonrpc/tests/test_factory.py
src/z3c/jsonrpc/tests/test_request.py