Metadata-Version: 1.1
Name: z3c.jsonrpc
Version: 0.7.2
Summary: JSON RPC server and client implementation for Zope3
Home-page: http://pypi.python.org/pypi/z3c.jsonrpc
Author: Roger Ineichen and the Zope Community
Author-email: zope-dev@zope.org
License: ZPL 2.1
Keywords: zope3 z3c json rpc json-rpc server client
Platform: UNKNOWN
Classifier: Development Status :: 5 - Production/Stable
Classifier: Environment :: Web Environment
Classifier: Intended Audience :: Developers
Classifier: License :: OSI Approved :: Zope Public License
Classifier: Programming Language :: Python
Classifier: Natural Language :: English
Classifier: Operating System :: OS Independent
Classifier: Topic :: Internet :: WWW/HTTP
Classifier: Framework :: Zope3
